ReactBitsZhongwenban/README.md
ReactBitsZhongwenban/__init__.py
ReactBitsZhongwenban/__main__.py
ReactBitsZhongwenban/file.epub
ReactBitsZhongwenban/index.html
ReactBitsZhongwenban/css/__init__.py
ReactBitsZhongwenban/css/annotations.css
ReactBitsZhongwenban/css/main.css
ReactBitsZhongwenban/css/normalize.css
ReactBitsZhongwenban/css/popup.css
ReactBitsZhongwenban/font/__init__.py
ReactBitsZhongwenban/font/fontello.eot
ReactBitsZhongwenban/font/fontello.svg
ReactBitsZhongwenban/font/fontello.ttf
ReactBitsZhongwenban/font/fontello.woff
ReactBitsZhongwenban/img/__init__.py
ReactBitsZhongwenban/img/annotator-glyph-sprite.png
ReactBitsZhongwenban/img/annotator-icon-sprite.png
ReactBitsZhongwenban/img/apple-touch-icon.png
ReactBitsZhongwenban/img/cancelfullscreen.png
ReactBitsZhongwenban/img/close.png
ReactBitsZhongwenban/img/fullscreen.png
ReactBitsZhongwenban/img/loader.gif
ReactBitsZhongwenban/img/menu-icon.png
ReactBitsZhongwenban/img/save.png
ReactBitsZhongwenban/img/saved.png
ReactBitsZhongwenban/img/settings-s.png
ReactBitsZhongwenban/img/settings.png
ReactBitsZhongwenban/img/star.png
ReactBitsZhongwenban/js/__init__.py
ReactBitsZhongwenban/js/epub.js
ReactBitsZhongwenban/js/epub.min.js
ReactBitsZhongwenban/js/epub.min.map
ReactBitsZhongwenban/js/hooks.min.js
ReactBitsZhongwenban/js/hooks.min.map
ReactBitsZhongwenban/js/reader.js
ReactBitsZhongwenban/js/reader.js.map
ReactBitsZhongwenban/js/reader.min.js
ReactBitsZhongwenban/js/reader.min.map
ReactBitsZhongwenban/js/hooks/__init__.py
ReactBitsZhongwenban/js/hooks/extensions/__init__.py
ReactBitsZhongwenban/js/hooks/extensions/highlight.js
ReactBitsZhongwenban/js/libs/__init__.py
ReactBitsZhongwenban/js/libs/jquery.min.js
ReactBitsZhongwenban/js/libs/localforage.min.js
ReactBitsZhongwenban/js/libs/screenfull.js
ReactBitsZhongwenban/js/libs/screenfull.min.js
ReactBitsZhongwenban/js/libs/zip.min.js
ReactBitsZhongwenban/js/plugins/__init__.py
ReactBitsZhongwenban/js/plugins/hypothesis.js
react_bits_zhongwenban-2024.3.2.0.dist-info/METADATA
react_bits_zhongwenban-2024.3.2.0.dist-info/WHEEL
react_bits_zhongwenban-2024.3.2.0.dist-info/entry_points.txt
react_bits_zhongwenban-2024.3.2.0.dist-info/top_level.txt
react_bits_zhongwenban-2024.3.2.0.dist-info/RECORD
